mbf_qualitycontrol/__init__.py
mbf_qualitycontrol/testing/__init__.py
mbf_qualitycontrol/testing/fixtures.py
mbf_qualitycontrol-0.1.dist-info/AUTHORS.rst
mbf_qualitycontrol-0.1.dist-info/LICENSE.txt
mbf_qualitycontrol-0.1.dist-info/METADATA
mbf_qualitycontrol-0.1.dist-info/WHEEL
mbf_qualitycontrol-0.1.dist-info/top_level.txt
mbf_qualitycontrol-0.1.dist-info/RECORD
