Metadata-Version: 2.1
Name: mbf-qualitycontrol
Version: 0.1
Summary: various file formats
Home-page: https://github.com/TyberiusPrime/mbf_qualitycontrol
Author: Florian Finkernagel
Author-email: finkernagel@imt.uni-marburg.de
License: mit
Platform: any
Classifier: Development Status :: 4 - Beta
Classifier: Programming Language :: Python
Requires-Python: >=3.6
Requires-Dist: numpy
Requires-Dist: pandas
Provides-Extra: doc
Requires-Dist: numpydoc ; extra == 'doc'
Requires-Dist: sphinx ; extra == 'doc'
Requires-Dist: sphinx-bootstrap-theme ; extra == 'doc'
Provides-Extra: testing
Requires-Dist: pytest ; extra == 'testing'
Requires-Dist: pytest-cov ; extra == 'testing'
Requires-Dist: pytest-icdiff ; extra == 'testing'
Requires-Dist: requests-mock ; extra == 'testing'
